pyqvd/__init__.py
pyqvd/io/__init__.py
pyqvd/io/format.py
pyqvd/io/reader.py
pyqvd/io/writer.py
pyqvd/qvd.py
pyqvd-2.3.0.dist-info/licenses/LICENSE.md
pyqvd-2.3.0.dist-info/METADATA
pyqvd-2.3.0.dist-info/WHEEL
pyqvd-2.3.0.dist-info/RECORD
