Metadata-Version: 2.4
Name: pyqvd
Version: 2.3.0
Summary: Utility library for reading/writing Qlik View Data (QVD) files in Python.
License: MIT
License-File: LICENSE.md
Keywords: qlik,qvd,qlik sense,qlik view,pandas
Author: Constantin Müller
Author-email: info@mueller-constantin.de
Requires-Python: >=3.9
Classifier: Development Status :: 5 - Production/Stable
Classifier: Intended Audience :: Developers
Classifier: License :: OSI Approved :: MIT License
Classifier: Natural Language :: English
Classifier: Programming Language :: Python :: 3
Classifier: Programming Language :: Python :: 3.9
Classifier: Programming Language :: Python :: 3.10
Classifier: Programming Language :: Python :: 3.11
Classifier: Programming Language :: Python :: 3.12
Classifier: Programming Language :: Python :: 3.13
Classifier: Programming Language :: Python :: 3.14
Classifier: Programming Language :: Python :: 3.8
Provides-Extra: pandas
Requires-Dist: pandas (>=2.2,<3.0) ; extra == "pandas"
Requires-Dist: tabulate (>=0.9,<0.10)
Project-URL: Documentation, https://pyqvd.readthedocs.io
Project-URL: Homepage, https://github.com/MuellerConstantin/PyQvd
Project-URL: Repository, https://github.com/MuellerConstantin/PyQvd
